ghrepo_stats/__init__.py
ghrepo_stats/show_gh_stats.py
test/__init__.py
test/conftest.py
test/test_configreader.py
test/test_issue_pr_stats.py
test/test_star_stats.py
test/utils.py
ghrepo_stats-0.5.5.dist-info/LICENSE
ghrepo_stats-0.5.5.dist-info/METADATA
ghrepo_stats-0.5.5.dist-info/WHEEL
ghrepo_stats-0.5.5.dist-info/entry_points.txt
ghrepo_stats-0.5.5.dist-info/top_level.txt
ghrepo_stats-0.5.5.dist-info/RECORD
