Metadata-Version: 2.2
Name: ghrepo-stats
Version: 0.5.5
Summary: Command line tools for GitHub repo statistics
Home-page: http://github.com/mrbean-bremen/ghrepo-stats
Author: mrbean-bremen
Author-email: hansemrbean@googlemail.com
License: MIT
Keywords: github,python
Classifier: License :: OSI Approved :: MIT License
Classifier: Intended Audience :: Developers
Classifier: Development Status :: 4 - Beta
Classifier: Environment :: Console
Classifier: Programming Language :: Python
Classifier: Programming Language :: Python :: 3
Classifier: Operating System :: POSIX :: Linux
Classifier: Operating System :: MacOS
Classifier: Operating System :: Microsoft :: Windows
Classifier: Topic :: Utilities
License-File: LICENSE
Requires-Dist: pygithub
Requires-Dist: matplotlib
Requires-Dist: requests
Requires-Dist: beautifulsoup4
